{"path":"goninjathief/","type":"large","id":"goninjathief","title":"Go! Ninja Thief","content":[{"name":"goninjathief_list_hard_char.png","text":"Go! Ninja Thief 1"},{"name":"goninjathief_main_char_delta.png","text":"Go! Ninja Thief 2"},{"name":"goninjathief_main_char_miranda.png","text":"Go! Ninja Thief 3"},{"name":"goninjathief_main_char_phantom.png","text":"Go! Ninja Thief 4"},{"name":"goninjathief_main_char_poli.png","text":"Go! Ninja Thief 5"},{"name":"goninjathief_main_char_quency.png","text":"Go! Ninja Thief 6"}]}