{"path":"story10/","type":"large","id":"story10","title":"Chapter 41 to 42","notice":"Compressed from 240mb ( for some reason ) to 22mb","content":[{"name":"EventScene_Chap_41_01.webp","text":"Chapter 41 to 42 1"},{"name":"EventScene_Chap_41_02_1.webp","text":"Chapter 41 to 42 2"},{"name":"EventScene_Chap_41_02_2.webp","text":"Chapter 41 to 42 3"},{"name":"EventScene_Chap_41_03.webp","text":"Chapter 41 to 42 4"},{"name":"EventScene_Chap_41_04_1.webp","text":"Chapter 41 to 42 5"},{"name":"EventScene_Chap_41_04_2.webp","text":"Chapter 41 to 42 6"},{"name":"EventScene_Chap_41_04_3.webp","text":"Chapter 41 to 42 7"},{"name":"EventScene_Chap_41_05.webp","text":"Chapter 41 to 42 8"},{"name":"EventScene_Chap_41_06.webp","text":"Chapter 41 to 42 9"},{"name":"EventScene_Chap_41_07.webp","text":"Chapter 41 to 42 10"},{"name":"EventScene_Chap_41_08_1.webp","text":"Chapter 41 to 42 11"},{"name":"EventScene_Chap_41_08_2.webp","text":"Chapter 41 to 42 12"},{"name":"EventScene_Chap_41_08_3.webp","text":"Chapter 41 to 42 13"},{"name":"EventScene_Chap_41_09_1.webp","text":"Chapter 41 to 42 14"},{"name":"EventScene_Chap_41_09_2.webp","text":"Chapter 41 to 42 15"},{"name":"EventScene_Chap_41_09_3.webp","text":"Chapter 41 to 42 16"},{"name":"EventScene_Chap_42_01_1.webp","text":"Chapter 41 to 42 17"},{"name":"EventScene_Chap_42_01_2.webp","text":"Chapter 41 to 42 18"},{"name":"EventScene_Chap_42_02_1.webp","text":"Chapter 41 to 42 19"},{"name":"EventScene_Chap_42_02_2.webp","text":"Chapter 41 to 42 20"},{"name":"EventScene_Chap_42_02_3.webp","text":"Chapter 41 to 42 21"},{"name":"EventScene_Chap_42_03_1.webp","text":"Chapter 41 to 42 22"},{"name":"EventScene_Chap_42_03_2.webp","text":"Chapter 41 to 42 23"},{"name":"EventScene_Chap_42_04_1.webp","text":"Chapter 41 to 42 24"},{"name":"EventScene_Chap_42_04_2.webp","text":"Chapter 41 to 42 25"},{"name":"EventScene_Chap_42_04_3.webp","text":"Chapter 41 to 42 26"},{"name":"EventScene_Chap_42_04_4.webp","text":"Chapter 41 to 42 27"},{"name":"EventScene_Chap_42_05_1.webp","text":"Chapter 41 to 42 28"},{"name":"EventScene_Chap_42_05_2.webp","text":"Chapter 41 to 42 29"},{"name":"EventScene_Chap_42_05_3.webp","text":"Chapter 41 to 42 30"},{"name":"EventScene_Chap_42_06.webp","text":"Chapter 41 to 42 31"},{"name":"EventScene_Chap_42_07_1.webp","text":"Chapter 41 to 42 32"},{"name":"EventScene_Chap_42_07_2.webp","text":"Chapter 41 to 42 33"},{"name":"EventScene_Chap_42_07_3.webp","text":"Chapter 41 to 42 34"},{"name":"EventScene_Chap_42_08_1.webp","text":"Chapter 41 to 42 35"},{"name":"EventScene_Chap_42_08_2.webp","text":"Chapter 41 to 42 36"},{"name":"EventScene_Chap_42_09.webp","text":"Chapter 41 to 42 37"},{"name":"EventScene_Chap_42_10.webp","text":"Chapter 41 to 42 38"},{"name":"EventScene_Chap_42_11.webp","text":"Chapter 41 to 42 39"},{"name":"EventScene_Chap_42_11_1.webp","text":"Chapter 41 to 42 40"},{"name":"EventScene_Chap_42_11_2.webp","text":"Chapter 41 to 42 41"},{"name":"EventScene_Chap_42_12_1.webp","text":"Chapter 41 to 42 42"},{"name":"EventScene_Chap_42_12_2.webp","text":"Chapter 41 to 42 43"},{"name":"EventScene_Chap_42_12_3.webp","text":"Chapter 41 to 42 44"}]}